pyaconf/__init__.py
pyaconf/pyaconf.py
pyaconf-0.7.2.data/scripts/pyaconf_render
pyaconf-0.7.2.dist-info/AUTHORS
pyaconf-0.7.2.dist-info/LICENSE
pyaconf-0.7.2.dist-info/METADATA
pyaconf-0.7.2.dist-info/WHEEL
pyaconf-0.7.2.dist-info/top_level.txt
pyaconf-0.7.2.dist-info/RECORD
