Metadata-Version: 2.1
Name: pyaconf
Version: 0.7.2
Summary: Yet another config library that is built around python dictionary and supports dynamic python, json, yaml, and ini formats with inheritance with Jinji2 templates
Home-page: https://github.com/ikhomyakov/pyaconf
Author: ikh software, inc.
Author-email: ikh@ikhsoftware.com
License: UNKNOWN
Project-URL: Bug Reports, https://github.com/ikhomyakov/pyaconf/issues
Platform: UNKNOWN
Classifier: Programming Language :: Python :: 3
Classifier: License :: OSI Approved :: BSD License
Classifier: Operating System :: OS Independent
Requires-Python: >= 3.7
Requires-Dist: pyyaml (>=5.1)
Requires-Dist: jinja2 (>=2.10)
